modules/immed_gen.sv
/*
Define constant opcode values
*/
localparam logic [6:0] OP_LUI = 7'b0110111;
localparam logic [6:0] OP_AUIPC = 7'b0010111;
localparam logic [6:0] OP_JAL = 7'b1101111;
localparam logic [6:0] OP_JALR = 7'b1100111;
localparam logic [6:0] OP_BRANCH = 7'b1100011;
localparam logic [6:0] OP_LOAD = 7'b0000011;
localparam logic [6:0] OP_STORE = 7'b0100011;
localparam logic [6:0] OP_REG = 7'b0110011;
localparam logic [6:0] OP_IMM = 7'b0010011;

module immed_gen(
    input logic [31:0] instruction,
    output logic [31:0] immediate
);

    logic [6:0] opcode;
    assign opcode = instruction[6:0];
    always_comb begin
        case (opcode)
            OP_LOAD, OP_JALR, OP_IMM: begin
                immediate = {{20{instruction[31]}}, instruction[31:20]};
            end
            OP_STORE: begin
                immediate = {{20{instruction[31]}}, instruction[31:25], instruction[11:7]};
            end
            OP_BRANCH: begin
                immediate = {{20{instruction[31]}}, instruction[7], instruction[30:25], instruction[11:8], 1'b0};
            end
            OP_JAL: begin
                immediate = {{12{instruction[31]}}, instruction[19:12], instruction[20], instruction[30:21], 1'b0};
            end
            OP_AUIPC, OP_LUI: begin
                immediate = {instruction[31:12], 12'b0};
            end
            default: begin
                immediate = 32'b0;
            end
        endcase  
    end
endmodule

immed_gen_tb.sv
`timescale 1ns/1ns
`include "modules/immed_gen.sv"

module immed_gen_tb;

    logic [31:0] instruction;
    logic [31:0] immediate;

    immed_gen uut (
        .instruction(instruction),
        .immediate(immediate)
    );

    task test_immed(input [31:0] instr, input [31:0] expected);
        instruction = instr;
        #1; // wait for combinational logic
        if (immediate !== expected) begin
            $display("FAILED: instruction = 0x%08h | expected = 0x%08h | got = 0x%08h", instr, expected, immediate);
        end else begin
            $display("PASSED: instruction = 0x%08h | immediate = 0x%08h", instr, immediate);
        end
    endtask

    initial begin
        $dumpfile("immed_gen_tb.vcd");
        $dumpvars(0, immed_gen_tb);
        $display("Starting Immediate Generator Tests...");

        // I-Type: LW (opcode = 0000011)
        test_immed(32'b000000000001_00000_010_00001_0000011, 32'h00000001);

        // I-Type: SLLI (opcode = 0010011, funct3 = 001)
        test_immed(32'b0000000_00010_00001_001_00001_0010011, 32'h00000002); // shift amount = 2

        // S-Type: SW (opcode = 0100011)
        test_immed(32'b0000001_00010_00001_010_00010_0100011, 32'h00000022);

        // B-Type: BEQ (opcode = 1100011)
        test_immed(32'b000000000010000010000000111100011, 32'h00000802);

        // J-Type: JAL (opcode = 1101111)
        test_immed(32'b11111111111111111111000001101111, 32'hFFFFFFFE);

        // U-Type: LUI (opcode = 0110111)
        test_immed(32'b00010010001101000101_00001_0110111, 32'h12345000);

        // U-Type: AUIPC (opcode = 0010111)
        test_immed(32'b00000000000100110000_00001_0010111, 32'h00130000);

        test_immed(32'b11111111101100000000001010010011, 32'hfffffffb);

        // Default: unsupported opcode → immediate = 0
        test_immed(32'hFFFFFFFF, 32'h00000000);

        $display("All tests complete.");
        $finish;
    end
endmodule

sim_res/immed_gen_tb.vcd
$date
	Sun Apr 20 19:23:35 2025
$end
$version
	Icarus Verilog
$end
$timescale
	1ns
$end
$scope module immed_gen_tb $end
$var wire 32 ! immediate [31:0] $end
$var reg 32 " instruction [31:0] $end
$scope module uut $end
$var wire 32 # instruction [31:0] $end
$var wire 7 $ opcode [6:0] $end
$var reg 32 % immediate [31:0] $end
$upscope $end
$scope task test_immed $end
$var reg 32 & expected [31:0] $end
$var reg 32 ' instr [31:0] $end
$upscope $end
$upscope $end
$enddefinitions $end
$comment Show the parameter values. $end
$dumpall
$end
#0
$dumpvars
b100000010000010000011 '
b1 &
b1 %
b11 $
b100000010000010000011 #
b100000010000010000011 "
b1 !
$end
#1
b10 !
b10 %
b10011 $
b1000001001000010010011 "
b1000001001000010010011 #
b10 &
b1000001001000010010011 '
#2
b100010 !
b100010 %
b100011 $
b10001000001010000100100011 "
b10001000001010000100100011 #
b100010 &
b10001000001010000100100011 '
#3
b100000000010 !
b100000000010 %
b1100011 $
b10000010000000111100011 "
b10000010000000111100011 #
b100000000010 &
b10000010000000111100011 '
#4
b11111111111111111111111111111110 !
b11111111111111111111111111111110 %
b1101111 $
b11111111111111111111000001101111 "
b11111111111111111111000001101111 #
b11111111111111111111111111111110 &
b11111111111111111111000001101111 '
#5
b10010001101000101000000000000 !
b10010001101000101000000000000 %
b110111 $
b10010001101000101000010110111 "
b10010001101000101000010110111 #
b10010001101000101000000000000 &
b10010001101000101000010110111 '
#6
b100110000000000000000 !
b100110000000000000000 %
b10111 $
b100110000000010010111 "
b100110000000010010111 #
b100110000000000000000 &
b100110000000010010111 '
#7
b0 !
b0 %
b1111111 $
b11111111111111111111111111111111 "
b11111111111111111111111111111111 #
b0 &
b11111111111111111111111111111111 '
